sql_models/SQLCamelModel.py
sql_models/__init__.py
sql_models/manufacturer/ManufacturerEntity.py
sql_models/manufacturer/NewManufacturer.py
sql_models/manufacturer/__init__.py
sql_models/motorcycle_model/MotorcycleModel.py
sql_models/motorcycle_model/MotorcycleModelEntity.py
sql_models/motorcycle_model/__init__.py
sql_models/motorcycle_model/sections/MotorcycleModelSections.py
sql_models/motorcycle_model/sections/__init__.py
sql_models/motorcycle_model/sections/abs/AbsProblem.py
sql_models/motorcycle_model/sections/abs/AbsSection.py
sql_models/motorcycle_model/sections/abs/__init__.py
sql_models/motorcycle_model/sections/autodiagnosis/AutodiagnosisFault.py
sql_models/motorcycle_model/sections/autodiagnosis/AutodiagnosisSection.py
sql_models/motorcycle_model/sections/autodiagnosis/__init__.py
sql_models/motorcycle_model/sections/components/Component.py
sql_models/motorcycle_model/sections/components/ComponentsSection.py
sql_models/motorcycle_model/sections/components/__init__.py
sql_models/motorcycle_model/sections/custom_electrical_scheme/CustomElectricalScheme.py
sql_models/motorcycle_model/sections/custom_electrical_scheme/__init__.py
sql_models/motorcycle_model/sections/distribution/DataBlock.py
sql_models/motorcycle_model/sections/distribution/DistributionSection.py
sql_models/motorcycle_model/sections/distribution/__init__.py
sql_models/motorcycle_model/sections/electronic/ElectronicComponentAttribute.py
sql_models/motorcycle_model/sections/electronic/ElectronicElement.py
sql_models/motorcycle_model/sections/electronic/ElectronicElementComponent.py
sql_models/motorcycle_model/sections/electronic/ElectronicSection.py
sql_models/motorcycle_model/sections/electronic/__init__.py
sql_models/motorcycle_model/sections/engine/EngineElementAttribute.py
sql_models/motorcycle_model/sections/engine/EngineSection.py
sql_models/motorcycle_model/sections/engine/EngineSubsection.py
sql_models/motorcycle_model/sections/engine/EngineSubsectionElement.py
sql_models_infomoto-0.4.1.dist-info/WHEEL
sql_models_infomoto-0.4.1.dist-info/METADATA
sql_models_infomoto-0.4.1.dist-info/RECORD
