Metadata-Version: 2.1
Name: sql-models-infomoto
Version: 0.4.1
Summary: 
Author: todotom
Author-email: tomasdarioam@protonmail.com
Requires-Python: ==3.10.4
Classifier: Programming Language :: Python :: 3
Requires-Dist: camel-model (==0.1.2)
Requires-Dist: sqlmodel (==0.0.6)
